README.md
setup.cfg
setup.py
server_check/__init__.py
server_check/server_check.py
time_server_analysis.egg-info/PKG-INFO
time_server_analysis.egg-info/SOURCES.txt
time_server_analysis.egg-info/dependency_links.txt
time_server_analysis.egg-info/top_level.txt